motiondev/__init__.py
motiondev/classes.py
motiondev/client.py
motiondev/errors.py
motiondev/http.py
motiondev-0.1.0.dist-info/LICENSE
motiondev-0.1.0.dist-info/METADATA
motiondev-0.1.0.dist-info/WHEEL
motiondev-0.1.0.dist-info/top_level.txt
motiondev-0.1.0.dist-info/RECORD
