Metadata-Version: 2.1
Name: motiondev
Version: 0.1.0
Summary: An asynchronous API wrapper for the Motion Development bot list API.
Home-page: https://github.com/itswilliboy/motiondev
Author: ItsWilliboy
Project-URL: Homepage, https://github.com/itswilliboy/motiondev
Project-URL: Issue Tracker, https://github.com/itswilliboy/motiondev/issues
Classifier: Development Status :: 3 - Alpha
Classifier: Intended Audience :: Developers
Classifier: Natural Language :: English
Classifier: Operating System :: OS Independent
Classifier: Programming Language :: Python :: 3.9
Classifier: Programming Language :: Python :: 3.10
Classifier: Programming Language :: Python :: 3.11
Requires-Python: >=3.7
License-File: LICENSE
Requires-Dist: aiohttp
